adbons-0.4.0.dist-info/DESCRIPTION.rst
adbons-0.4.0.dist-info/METADATA
adbons-0.4.0.dist-info/RECORD
adbons-0.4.0.dist-info/WHEEL
adbons-0.4.0.dist-info/entry_points.txt
adbons-0.4.0.dist-info/metadata.json
adbons-0.4.0.dist-info/top_level.txt
src/__init__.py
src/adb.py
src/adbons.py
src/config.py
src/commands/__init__.py
src/commands/adb_commands.py
src/commands/config_commands.py
test/__init__.py
test/test_adbons.py
